trboxcmp/XcmpByteFactory.py
trboxcmp/XcmpOpCodes.py
trboxcmp/__init__.py
trboxcmp/xcmp.py
trboxcmp/xnl.py
trboxcmp-0.0.6.dist-info/LICENSE.md
trboxcmp-0.0.6.dist-info/METADATA
trboxcmp-0.0.6.dist-info/WHEEL
trboxcmp-0.0.6.dist-info/top_level.txt
trboxcmp-0.0.6.dist-info/RECORD
