Metadata-Version: 2.1
Name: trboxcmp
Version: 0.0.6
Summary: A collection of libraries to handle the XCMP protocol for Motorola radios
Home-page: https://git.natnat.xyz/natalie/trboxcmp
Author: Natalie
Author-email: natalie@natnat.xyz
License: UNKNOWN
Project-URL: Bug Tracker, https://nowhere
Platform: UNKNOWN
Classifier: Programming Language :: Python :: 3
Classifier: License :: OSI Approved :: MIT License
Classifier: Operating System :: OS Independent
Requires-Python: >=3.6
License-File: LICENSE.md
